cs_logger/__init__.py
cs_logger/log_config.py
cs_logger-0.0.1.dist-info/METADATA
cs_logger-0.0.1.dist-info/WHEEL
cs_logger-0.0.1.dist-info/top_level.txt
cs_logger-0.0.1.dist-info/RECORD
