Metadata-Version: 2.1
Name: cs-logger
Version: 0.0.1
Summary: Set up logging config for your project
Author: Richard
Author-email: <rich_swainson@hotmail.co.uk>
Keywords: telegram,bot,api,wrapper
Classifier: Development Status :: 5 - Production/Stable
Classifier: Intended Audience :: Developers
Classifier: Programming Language :: Python :: 3
Classifier: Operating System :: OS Independent
